[{"data":[],"postid":"148475335184300_153515584680275"},{"data":[{"id":"10208408675328579","name":"Peacal Liu","type":"LIKE"},{"id":"10212283554073504","name":"李曉雯","type":"LIKE"}],"postid":"148475335184300_154687664552967"},{"data":[{"id":"10208408675328579","name":"Peacal Liu","type":"LIKE"},{"id":"10210812863777933","name":"Oban Cheng","type":"LIKE"}],"postid":"148475335184300_117784298278274"},{"data":[{"id":"10208408675328579","name":"Peacal Liu","type":"LIKE"},{"id":"10203219809533371","name":"Tai Yi-Heng","type":"LIKE"}],"postid":"148475335184300_154998581187220"},{"data":[{"id":"10208408675328579","name":"Peacal Liu","type":"LIKE"}],"postid":"148475335184300_146401552068263"},{"data":[{"id":"1302663493144931","name":"陳平道","type":"LIKE"},{"id":"1541447582553860","name":"陳武雄","type":"LIKE"},{"id":"1908202692770586","name":"聶志桂","type":"LIKE"},{"id":"1329146687164828","name":"朱永盛","type":"LIKE"},{"id":"1295912693811888","name":"Kenny Chen","type":"LIKE"},{"id":"879339375540329","name":"蔡木寶","type":"LIKE"},{"id":"1095913597153318","name":"Sheng-yu Chang","type":"LIKE"},{"id":"1047285712071363","name":"張裎璘","type":"LIKE"},{"id":"1572208556123659","name":"Wei-Houng Lee","type":"LIKE"},{"id":"10208408675328579","name":"Peacal Liu","type":"LIKE"},{"id":"10206683803725988","name":"施重任","type":"LIKE"},{"id":"10210812863777933","name":"Oban Cheng","type":"LIKE"},{"id":"1266167793402767","name":"Jia Ling Wu","type":"LIKE"},{"id":"1259921407375538","name":"李育嫺","type":"LIKE"}],"postid":"148475335184300_153513044680529"},{"data":[{"id":"1171313316222470","name":"蘇怡文","type":"LIKE"},{"id":"1302663493144931","name":"陳平道","type":"LIKE"},{"id":"1908202692770586","name":"聶志桂","type":"LIKE"},{"id":"1329146687164828","name":"朱永盛","type":"LIKE"},{"id":"879339375540329","name":"蔡木寶","type":"LIKE"},{"id":"1412233215508762","name":"Nicole Peng","type":"LIKE"},{"id":"1464671653553195","name":"侯政廉","type":"LIKE"},{"id":"1432251603527069","name":"李燦堂","type":"LIKE"},{"id":"1546174892068378","name":"Ya Wen Wu","type":"LIKE"},{"id":"1707110519306803","name":"江淑芬","type":"LIKE"},{"id":"1559313547415263","name":"Bun Lin","type":"LIKE"},{"id":"1402617459826808","name":"劉洋","type":"LIKE"},{"id":"1806931142657774","name":"Woan-Harn Yang","type":"LIKE"},{"id":"1572208556123659","name":"Wei-Houng Lee","type":"LIKE"},{"id":"10208408675328579","name":"Peacal Liu","type":"LIKE"},{"id":"10210812863777933","name":"Oban Cheng","type":"LIKE"},{"id":"1662803800415054","name":"Orange Hsieh","type":"LIKE"},{"id":"10209462595101531","name":"Hobert Meng-En Chiu","type":"LIKE"},{"id":"1436367416380374","name":"李小雯","type":"LIKE"},{"id":"1758810897468996","name":"蕭小飄","type":"LIKE"},{"id":"10155054439400932","name":"Sari Tolvanen","type":"LIKE"},{"id":"10153342109168078","name":"Fung Ka Keung","type":"LIKE"},{"id":"10154044579850326","name":"Fanny Lee","type":"LIKE"}],"postid":"148475335184300_154372184594615"},{"data":[{"id":"10208408675328579","name":"Peacal Liu","type":"LIKE"}],"postid":"148475335184300_154674001219560"},{"data":[{"id":"10208408675328579","name":"Peacal Liu","type":"LIKE"}],"postid":"148475335184300_162394287109322"},{"data":[{"id":"10209141459437997","name":"Rita Kerzen","type":"LIKE"},{"id":"10208408675328579","name":"Peacal Liu","type":"LIKE"},{"id":"10154512910679732","name":"Wayne Hsu","type":"LIKE"},{"id":"1705853119428933","name":"王冠傑","type":"LIKE"},{"id":"10155147213006839","name":"Michelle Yen","type":"LIKE"},{"id":"1259921407375538","name":"李育嫺","type":"LIKE"}],"postid":"148475335184300_118899124832183"},{"data":[],"postid":"148475335184300_155160261169563"},{"data":[],"postid":"148475335184300_150495511648949"},{"data":[{"id":"173991477646","name":"New Energy Portal","type":"LIKE"},{"id":"1259921407375538","name":"李育嫺","type":"LIKE"},{"id":"10153342109168078","name":"Fung Ka Keung","type":"LIKE"}],"postid":"148475335184300_150350328331234"},{"data":[{"id":"10212283554073504","name":"李曉雯","type":"LIKE"}],"postid":"148475335184300_147249061981219"},{"data":[],"postid":"148475335184300_158104760868776"},{"data":[{"id":"173991477646","name":"New Energy Portal","type":"LIKE"},{"id":"10209141459437997","name":"Rita Kerzen","type":"LIKE"},{"id":"10208408675328579","name":"Peacal Liu","type":"LIKE"},{"id":"10155147213006839","name":"Michelle Yen","type":"LIKE"},{"id":"1259921407375538","name":"李育嫺","type":"LIKE"}],"postid":"148475335184300_102076809854734"},{"data":[{"id":"1561719413852729","name":"胡達平","type":"LIKE"},{"id":"10155287011929560","name":"Rueya Cheng","type":"LIKE"},{"id":"1696272747057268","name":"Nico Lulu","type":"LIKE"},{"id":"1467926243222615","name":"Li Yenpei","type":"LIKE"},{"id":"1292353177529648","name":"林信桐","type":"LIKE"},{"id":"1984703095142232","name":"廖國棟","type":"LIKE"},{"id":"1252097068250896","name":"林易增","type":"LIKE"},{"id":"1869662929912623","name":"黃秀賢","type":"LIKE"},{"id":"1044385575693480","name":"張超傑","type":"LIKE"},{"id":"1578291428847930","name":"Sophie Kuo","type":"LIKE"},{"id":"1466008330085926","name":"Kevin Su","type":"LIKE"},{"id":"1458752440814031","name":"陳美雪","type":"LIKE"},{"id":"1180205218750648","name":"羅順達","type":"LIKE"},{"id":"1138532336292652","name":"吳長原","type":"LIKE"},{"id":"650571875144027","name":"蕭榮照","type":"LIKE"},{"id":"1937234189841517","name":"鄭謨緒","type":"LIKE"},{"id":"1543642782313041","name":"李復漢","type":"LIKE"},{"id":"703702499786374","name":"鄭金幼","type":"LIKE"},{"id":"1581160475237009","name":"Cherry Hsu","type":"LIKE"},{"id":"865248140272918","name":"Yu-teng  WU","type":"LIKE"},{"id":"173991477646","name":"New Energy Portal","type":"LIKE"},{"id":"10209141459437997","name":"Rita Kerzen","type":"LIKE"},{"id":"1394512477292053","name":"詹曉薑","type":"LIKE"},{"id":"1313623708752058","name":"Gusmao Brito Sidney","type":"LIKE"},{"id":"1369205343162563","name":"Cora Sin","type":"LIKE"},{"id":"214496301894362","name":"伊聖詩私房書櫃*Escents Bookcase","type":"LIKE"},{"id":"10212590242379842","name":"Chu Chen","type":"LIKE"},{"id":"10207834382002017","name":"Roger Su","type":"LIKE"},{"id":"10213507561663857","name":"Fan-Chun Meng","type":"LIKE"},{"id":"10212283554073504","name":"李曉雯","type":"LIKE"},{"id":"1366118570116760","name":"Kuan-yu Chen","type":"LIKE"}],"postid":"148475335184300_1610457269450"},{"data":[{"id":"1703974896279288","name":"Mrls Lin","type":"LIKE"},{"id":"1952195784805963","name":"葉誠","type":"LIKE"},{"id":"1302663493144931","name":"陳平道","type":"LIKE"},{"id":"876762865787275","name":"吳秀蘭","type":"LIKE"},{"id":"1528834703833404","name":"Leo Lin","type":"LIKE"},{"id":"10206673633385651","name":"張乃昌","type":"LIKE"},{"id":"10154602046372584","name":"曾多多","type":"LIKE"},{"id":"1461154903901540","name":"Ching Hsun Ko","type":"LIKE"},{"id":"1967708496797054","name":"洪義添","type":"LIKE"},{"id":"702780346592275","name":"洪碧華","type":"LIKE"},{"id":"1908202692770586","name":"聶志桂","type":"LIKE"},{"id":"1329146687164828","name":"朱永盛","type":"LIKE"},{"id":"1387510607944012","name":"陳人和","type":"LIKE"},{"id":"10155320975914727","name":"李昌霖","type":"LIKE"},{"id":"1154406991371464","name":"Jiean Shiang  Wang","type":"LIKE"},{"id":"1412233215508762","name":"Nicole Peng","type":"LIKE"},{"id":"10211560529381132","name":"Terence Teo","type":"LIKE"},{"id":"1794067273953133","name":"侯貞","type":"LIKE"},{"id":"10157351760445251","name":"Chia-Yi Meng","type":"LIKE"},{"id":"1453711248019592","name":"陳順謙","type":"LIKE"},{"id":"902700149858355","name":"高明和","type":"LIKE"},{"id":"1046698935419961","name":"Stacy Hou","type":"LIKE"},{"id":"10208550273127050","name":"方英豪","type":"LIKE"},{"id":"10158643739775570","name":"Hanlin Peng","type":"LIKE"},{"id":"10154800565349587","name":"Yung-Han Chang","type":"LIKE"},{"id":"1464671653553195","name":"侯政廉","type":"LIKE"},{"id":"651926298304097","name":"陳志邦","type":"LIKE"},{"id":"1323672094353771","name":"James Chiu","type":"LIKE"},{"id":"10209141459437997","name":"Rita Kerzen","type":"LIKE"},{"id":"10203800357244809","name":"Linda Chuang","type":"LIKE"},{"id":"173991477646","name":"New Energy Portal","type":"LIKE"},{"id":"884680298338322","name":"Selina  Hung","type":"LIKE"},{"id":"10155313944358497","name":"Aqua Grrl","type":"LIKE"},{"id":"10157566687830193","name":"Morgan Lin","type":"LIKE"},{"id":"1512270615458041","name":"陳義順","type":"LIKE"},{"id":"10155113754901815","name":"Sally Ann","type":"LIKE"},{"id":"1806931142657774","name":"Woan-Harn Yang","type":"LIKE"},{"id":"1572208556123659","name":"Wei-Houng Lee","type":"LIKE"},{"id":"1469772556372974","name":"郭秀","type":"LIKE"},{"id":"10154475720761232","name":"Chao-Jui Chou","type":"LIKE"},{"id":"10158775129965302","name":"Evelyn Lai","type":"LIKE"},{"id":"10211032987692732","name":"Afra Chen","type":"LIKE"},{"id":"10209202544210135","name":"Shih-hsun Huang","type":"LIKE"},{"id":"10207283863111117","name":"潘翰疆","type":"LIKE"},{"id":"1662803800415054","name":"Orange Hsieh","type":"LIKE"},{"id":"1705853119428933","name":"王冠傑","type":"LIKE"},{"id":"10212283554073504","name":"李曉雯","type":"LIKE"},{"id":"1257000744311965","name":"Wen Cheng Lee","type":"LIKE"},{"id":"1626883087322894","name":"Blue Lin","type":"LIKE"},{"id":"10156260774503065","name":"Fer Shira","type":"LIKE"}],"postid":"148475335184300_148507425181091"}]